README.md
setup.py
FacetClumps/Detect_Files.py
FacetClumps/FacetClumps_2D.py
FacetClumps/FacetClumps_3D.py
FacetClumps/Test_File.py
FacetClumps/__init__.py
FacetClumps.egg-info/PKG-INFO
FacetClumps.egg-info/SOURCES.txt
FacetClumps.egg-info/dependency_links.txt
FacetClumps.egg-info/top_level.txt