Metadata-Version: 2.1
Name: FacetClumps
Version: 0.2
Summary: FacetClumps: A molecular cloud clump detection algorithm based on Facet model
Author: Jiang Yu
Author-email: yujiang@pmo.ac.cn
